elrados/__init__.py
elrados/urls.py
elrados/utils.py
elrados/views.py
elrados/backend/__init__.py
elrados/backend/cache.py
elrados/backend/main.py
elrados/backend/management.py
elrados/backend/utils.py
elrados/static/bundle.js
elrados/static/bundle.js.map
elrados/static/font/JosefinSans-Regular.ttf
elrados/static/img/filter.svg
elrados/static/img/groups.svg
elrados/static/img/lock2.svg
elrados/static/img/open.svg
elrados/static/img/unlock2.svg
elrados/templates/base.html
elrados/templates/index.html
elrados-0.7.2.dist-info/LICENSE
elrados-0.7.2.dist-info/METADATA
elrados-0.7.2.dist-info/WHEEL
elrados-0.7.2.dist-info/entry_points.txt
elrados-0.7.2.dist-info/top_level.txt
elrados-0.7.2.dist-info/RECORD
