Metadata-Version: 2.1
Name: elrados
Version: 0.7.2
Summary: Frontend for django models and Rotest Testing Framework
Home-page: https://github.com/IamShobe/elrados
Author: Elran Shefer
Author-email: elran777@gmail.com
License: MIT
Keywords: rotest frontend
Platform: UNKNOWN
Classifier: License :: OSI Approved :: MIT License
Classifier: Intended Audience :: Developers
Classifier: Programming Language :: Python :: 2
Classifier: Programming Language :: Python :: 2.7
Classifier: Programming Language :: Python :: 3
Classifier: Programming Language :: Python :: 3.5
Classifier: Programming Language :: Python :: 3.6
Classifier: Programming Language :: Python :: 3.7
Classifier: Operating System :: Microsoft :: Windows
Classifier: Operating System :: POSIX
Classifier: Operating System :: Unix
Classifier: Operating System :: MacOS
Requires-Python: >=2.7,!=3.0.*,!=3.1.*,!=3.2.*,!=3.3.*,!=3.4.*
Requires-Dist: django (<1.9,>=1.8)
Requires-Dist: twisted
Requires-Dist: crochet
Requires-Dist: autobahn
Requires-Dist: rotest (>=7.0.0)
